test/__init__.py
test/wifi_conf_test.py
wifi_conf/__init__.py
wifi_conf/wifi_conf.py
wifi_conf/wifi_conf_client.py
wifi_conf/wifi_conf_daemon.py
wifi_conf/data/dnsmasq.conf
wifi_conf/data/hostapd
wifi_conf/data/hostapd.conf
wifi_conf/data/wifi_conf.service
wifi_conf-0.1.dev0.data/scripts/install_wifi_conf
wifi_conf-0.1.dev0.data/scripts/uninstall_wifi_conf
wifi_conf-0.1.dev0.dist-info/DESCRIPTION.rst
wifi_conf-0.1.dev0.dist-info/METADATA
wifi_conf-0.1.dev0.dist-info/RECORD
wifi_conf-0.1.dev0.dist-info/WHEEL
wifi_conf-0.1.dev0.dist-info/entry_points.txt
wifi_conf-0.1.dev0.dist-info/metadata.json
wifi_conf-0.1.dev0.dist-info/top_level.txt
