Metadata-Version: 2.0
Name: wifi-conf
Version: 0.1.dev0
Summary: Package for setting up AP for configuration of wifi on raspberry pi
Home-page: https://github.com/mbunse/wifi_conf
Author: Moritz Bunse
Author-email: moritz.bunse@gmail.com
License: MIT
Project-URL: Source Code, https://github.com/mbunse/wifi_conf
Keywords: wifi access point raspberry pi raspbian
Platform: UNKNOWN
Requires-Dist: python-version (>="3.5")
Requires-Dist: socket-client-server (>="0.5.dev3")
